{
	"short_url_accw1": "https://blog.repl.it/anyone-can-code-week1",
	"short_url_accw2": "https://blog.repl.it/anyone-can-code-week2",
	"short_url_accw3": "https://blog.repl.it/anyone-can-code-week3",
	"short_url_accw4": "https://blog.repl.it/anyone-can-code-week4",
	"short_url_accw5": "https://blog.repl.it/anyone-can-code-week5",
	"short_url_accw6": "https://blog.repl.it/anyone-can-code-week6",
	"short_url_accw7": "https://blog.repl.it/anyone-can-code-week7",
	"short_url_advoc": "https://repl.it/talk/announcements/Advent-of-Code-Sponsorship/81590",
	"short_url_ahvwvztw": "https://repl.it/@piemadd/firefox",
	"short_url_auvxllnp": "https://replit.com/@Coder100/PassionateGrowlingFlashmemory-i-am-pogger",
	"short_url_bfujrnbn": "https://repl.it/talk/share/Portfolio-Site/121985",
	"short_url_blog-iotests": "https://blog.repl.it/input-output-tests",
	"short_url_bqatjxbr": "https://repl.it/talk/share/Portfolio-Site/121985",
	"short_url_brfaevjr": "https://www.scotusblog.com/case-files/cases/google-llc-v-oracle-america-inc/",
	"short_url_cflfotea": "https://repl.it/@Spotandjake/chatter-20",
	"short_url_cj10": "https://repl.it/talk/announcements/Code-Jam-10/78974",
	"short_url_claim-sigcse21": "https://repl.it/claim?code=sigcse21",
	"short_url_cmrpkuvz": "https://repl.it/@PixelNinja/TOTP-Example",
	"short_url_csed-slack": "https://join.slack.com/t/replit-teachers/shared_invite/zt-47s89g9x-L_UwPS_UU1BBk_~JtIRWVQ",
	"short_url_ctzbfnlp": "https://blog.repl.it/teams-for-edu-fall-2020-improvements",
	"short_url_curriculum-abdat": "https://docs.repl.it/curriculum/abstractData",
	"short_url_curriculum-pyint": "https://docs.repl.it/curriculum/intermediatePython",
	"short_url_cxlyytte": "https://repl.it/@BrokenDevs/Freshclass",
	"short_url_dhezgwts": "https://repl.it/talk/share/Portfolio-Site/121985",
	"short_url_diukifyj": "https://replit.com/@YaacovIland/Waterwheel-Simulator",
	"short_url_enfeofcb": "https://replit.com/@PYTHORE3605/PhotoFilter",
	"short_url_euqsuwjm": "https://repl.it/@ykdojo/snake-game-but-youre-the-food",
	"short_url_fish_2021": "https://drive.google.com/drive/folders/1jhtW7jmtIJykKz5kZYmcxFXQ_wgFvQJU?usp=sharing",
	"short_url_ftydgwts": "https://repl.it/@rafrafraf/chrome-extension",
	"short_url_goqpqprm": "https://repl.it/@piemadd/Replitsh-v3",
	"short_url_hack_week_2021": "https://drive.google.com/drive/folders/18aO0e37egdna92XCHupgxJyBWMup3JHm?usp=sharing",
	"short_url_hbdpiero": "https://hbd-piero.lilykhan.repl.co/",
	"short_url_hdcgnfet": "https://replit.com/@SortaGames/sortacraftmodelmaker",
	"short_url_igurgxhh": "https://repl.it/@piemadd/Replitsh-v3",
	"short_url_ijc": "https://docs.repl.it/curriculum/introJava",
	"short_url_jopaopys": "https://repl.it/talk/share/Portfolio-Site/121985",
	"short_url_jovopjlm": "https://repl.it/@CodingCactus/new-portfolio-site",
	"short_url_joygcaze": "https://repl.it/@RhinoRunner/Adventure-game",
	"short_url_jwcohuqc": "https://repl.it/@KobeFF/CSS-Orbit",
	"short_url_loopback": "https://replitloopback.repl.co",
	"short_url_lvpoyuhw": "https://repl.it/talk/share/I-made-my-own-version-of-Python-in-JS-JS/83219",
	"short_url_lzogruvo": "https://repl.it/@KobeFF/CSS-Orbit",
	"short_url_mebrnnua": "https://cases.justia.com/federal/appellate-courts/cafc/13-1021/13-1021-2014-05-09.pdf?ts=1411173375",
	"short_url_milpntsa": "https://repl.it/@RhinoRunner/Adventure-game",
	"short_url_mixtut": "https://mixtape-tutorial.datadesigns.repl.co/",
	"short_url_mmniponi": "https://replit.xyz/",
	"short_url_mpkkdbur": "https://repl.it/@piemadd/firefox",
	"short_url_mtvzokiv": "https://www.c-span.org/video/?469263-1/google-v-oracle-america-oral-argument",
	"short_url_neyktlxr": "https://repl.it/talk/share/Portfolio-Site/121985",
	"short_url_nuogwslz": "https://replit.com/@SortaGames/sortacraftmodelmaker",
	"short_url_pfztxwcd": "https://repl.it/@piemadd/Replitsh-v3",
	"short_url_qbzxorph": "https://repl.it/@piemadd/Replitsh-v3",
	"short_url_replit-community-social": "https://jobs.lever.co/replit/cd957164-1849-4fb5-aac9-fc317e29966f",
	"short_url_replit-data": "https://jobs.lever.co/replit/c5350e26-07b1-4cb4-9e88-5e0037e17fdc",
	"short_url_replit-designer": "https://jobs.lever.co/replit/4ef495be-6ced-42d9-bcc1-3c6f57a346bd",
	"short_url_replit-ed_csm": "https://jobs.lever.co/replit/ee097258-fdee-4cd5-8a23-c36d2ad2eb77",
	"short_url_replit-executive-assistant": "https://jobs.lever.co/replit/fed26db1-62bf-4434-83c0-6d90b1806660",
	"short_url_replit-growth": "https://jobs.lever.co/replit/c3077d40-7a20-48f1-af86-900060db9c26",
	"short_url_replit-intern": "https://jobs.lever.co/replit/37e93ef3-9329-426a-8371-96865959ae1b",
	"short_url_replit-new-talent": "https://jobs.lever.co/replit/cf1af9bb-87b2-4653-a9ed-936e21fe5ac4",
	"short_url_replit-platform": "https://jobs.lever.co/replit/19145b18-c8d5-487f-99f8-e765007bce01",
	"short_url_replit-product": "https://jobs.lever.co/replit/f1caf4a5-0516-44e6-ac3b-a80d379339ad",
	"short_url_replit-sre": "https://jobs.lever.co/replit/a0fbd9bf-1a86-4b1e-8c59-3a60e8bd32ef",
	"short_url_replit-teacher-success": "https://jobs.lever.co/replit/ee097258-fdee-4cd5-8a23-c36d2ad2eb77",
	"short_url_rjhhtdql": "https://repl.it/@KobeFF/CSS-Orbit",
	"short_url_rtp_2-5-3": "https://repl.it/talk/share/Replitsh-Replits-Official-URL-Shortener/79778",
	"short_url_stgnhpor": "https://repl.it/@piemadd/firefox",
	"short_url_tdogdnml": "https://repl.it/@galaxyraider9/Ai",
	"short_url_torkey": "https://repl.it/@piemadd/cyborg-turkey",
	"short_url_ugvrpvht": "https://repl.it/@piemadd/Replitsh-v3",
	"short_url_upajzvjp": "https://repl.it/@piemadd/Replitsh-v3",
	"short_url_weekly_wins_2021": "https://drive.google.com/drive/folders/14nm3bKEg6P_DjfZW5NCRiWkKa7VNQv4d?usp=sharing",
	"short_url_wlhhldpl": "https://repl.it/@piemadd/Replitsh-v3",
	"short_url_wlzwdvor": "https://repl.it/@piemadd/Replitsh-v3",
	"short_url_xmsoyyvo": "https://www.youtube.com/channel/UChBJtu4BhT8b8t9Qe9R-EZg",
	"short_url_xrgukhpn": "https://repl.it/@Crosis/Gepl-Chat",
	"short_url_yjmhaahr": "https://repl.it/@piemadd/ClutteredSecondhandCookies",
	"short_url_zubthmur": "https://jobs.lever.co/replit/c5350e26-07b1-4cb4-9e88-5e0037e17fdc",
	"social_media_ahvwvztw": {
		"title": "Firefox",
		"username": "Piemadd",
		"talk": "",
		"code": "print('1')\r\nprint('2')\r\nprint('3')\r\nprint('4')\r\nprint('5')\r\nprint('6')\r\nprint('7')\r\nprint('8')\r\nprint('9')\r\nprint('10')\r\nprint('11')\r\nprint('12')\r\nprint('13')\r\nprint('14')\r\nprint('15')"
	},
	"social_media_auvxllnp": {
		"title": "Mind Reader",
		"username": "Coder100",
		"talk": "https://replit.com/talk/share/Mind-Reader/127565",
		"code": "#include <ctime>\r\n#include <chrono>\r\n#include <thread>\r\n#include <cstdlib>\r\n#include <iostream>\r\n\r\n#include \"maths.h\"\r\n\r\n\r\nint main() {\r\n\tstd::srand(std::time(nullptr));\r\n\r\n\twhile (true) {\r\n\t\tstd::vector<Operation> choice = types[std::rand() % types.size()];\r\n\t\tdouble output = 0;\r\n\r\n\t\tstd::cout << \"\\x1b[94mThink of a number\\x1b[0m.\"\" \\x1b[92mAny number\\x1b[0m!\" << std::endl;\r\n\r\n\t\tfor (Operation op : choice) {\r\n\t\t\tdouble amt = op.is_num ? 0 : op.amt;\r\n\t\t\tswitch (op.type) {\r\n\t\t\tcase Type::Plus: output += amt; break;\r\n\t\t\tcase Type::Minus: output -= amt; break;\r\n\t\t\tcase Type::Times: output *= amt; break;\r\n\t\t\tcase Type::Divide: output /= amt; break;"
	},
	"social_media_cflfotea": {
		"title": "chatter-20",
		"username": "Spotandjake",
		"talk": ""
	},
	"social_media_cmrpkuvz": {
		"title": "TOTP-Example",
		"username": "PixelNinja",
		"talk": ""
	},
	"social_media_cxlyytte": {
		"title": "Freshclass",
		"username": "BrokenDevs",
		"talk": "https://repl.it/talk/share/Freshclass-CSS-Remade/127018",
		"code": "@import url(https://necolas.github.io/normalize.css/latest/normalize.css);\r\n:root {\r\n    --white: #fff;\r\n    --black: #000;\r\n    --color: #000;\r\n    --red: #f13939;\r\n    --redorange: #f66e3b;\r\n    --orange: #f19b26;\r\n    --orangeyellow: #edc022;\r\n    --yellow: #f3ed1d;\r\n    --yellowgreen: #c9f31d;\r\n    --green: #1bcb39;\r\n    --greenblue: #25c197;\r\n    --blue: #0c67f2;\r\n    --bluepurple: #5c0cf2;\r\n    --purple: #a730f9;\r\n    --purplered: #f743bb;\r\n}\r\n*,\r\n::after,\r\n::before {\r\n    box-sizing: border-box;\r\n    margin: 0;\r\n    padding: 0;\r\n}"
	},
	"social_media_diukifyj": {
		"title": "Waterwheel Simulator",
		"username": "YaacovIland",
		"talk": "https://replit.com/talk/share/Chaos-Water-Wheel/125953",
		"code": "import pygame\r\nfrom math import *\r\n\r\nprint(\"Start\")\r\n\r\nwhite = (255, 255, 255)\r\nlgrey = (225, 225, 225)\r\nblue = (0, 0, 200)\r\nbdim = 80  # short for bucket dimension\r\n\r\nclass Wheel:\r\n  def __init__(self, x, y, size):\r\n    self.x = x\r\n    self.y = y\r\n    self.size = size\r\n    self.colour = white\r\n    self.thickness = 0\r\n    self.angle = 0\r\n    self.buckets = []\r\n    self.default_capacity = bdim\r\n\r\n  def display(self):\r\n    pygame.draw.circle(screen, self.colour, (self.x, self.y), self.size, self.thickness)\r\n    #print(\"Wheel drawn with angle\", self.angle, \"centered at\", self.x, \",\", self.y)\r\n    for bucket in self.buckets:"
	},
	"social_media_enfeofcb": {
		"title": "PhotoFilter",
		"username": "PYTHORE3605",
		"talk": "https://replit.com/talk/share/PHOTOFILTER/127064",
		"code": "#imports the needed info from library\r\nfrom PIL import Image \r\nimport os, random\r\nfrom filters import *\r\n#defines clear screan\r\ndef clear():  \r\n\tos.system('clear')\r\n#defines the starting code\r\ndef start():\r\n\tglobal img\r\n#deleates the last eddited photo\r\n\tif os.path.exists(\"newImage.jpg\"):\r\n\t\tos.remove(\"newImage.jpg\")\r\n#asks the user what image they want to use\r\n\tvar = int(input(\"Enter the number of what image you want:\\n\"))\t\r\n\t#makes sure that the user inputed a correct number\r\n\twhile var >=6 or var <=0:\r\n\t\tclear()\r\n\t\tprint('ERROR 2 | INVALID INPUT')\r\n\t\tvar = int(input(\"Enter the number of what image you want:\\n\"))\r\n\timg = Image.open('img/image'+str(var)+'.jpg')\r\n\tclear()\r\n#rescales the image\r\n\twidth = img.width\r\n\theight = img.height"
	},
	"social_media_euqsuwjm": {
		"title": "Snake Game But Youre The Food",
		"username": "Ykdojo",
		"talk": "https://repl.it/talk/share/snake-game-but-youre-the-food/126048",
		"code": "from blessed import Terminal\r\nimport random\r\nimport copy\r\nfrom collections import deque\r\n\r\nterm = Terminal()\r\nUP = term.KEY_UP\r\nRIGHT = term.KEY_RIGHT\r\nLEFT = term.KEY_LEFT\r\nDOWN = term.KEY_DOWN\r\nDIRECTIONS = [LEFT, UP, RIGHT, DOWN]\r\nMOVEMENT_MAP = {LEFT: [0, -1], UP: [-1, 0], RIGHT: [0, 1], DOWN: [1, 0]}\r\nWASD_MAP = {'w': UP, 'a': LEFT, 's': DOWN, 'd': RIGHT, 'W': UP, 'A': LEFT, 'S': DOWN, 'D': RIGHT}\r\ndead = False\r\n\r\n# -------CONFIG--------\r\nBORDER = '\u2b1c\ufe0f'\r\nBODY = '\ud83d\udfe9'\r\nHEAD = '\ud83d\udfe5'\r\nSPACE = ' '\r\nAPPLE = '\ud83c\udf4e'\r\n\r\n# initial snake position\r\nsnake = deque([[6, 5], [6, 4], [6, 3]])\r\n# initial food position"
	},
	"social_media_ftydgwts": {
		"title": "repldm alpha 0.0.1 - direct messaging in repl.it!",
		"username": "MarcusWeinberger",
		"talk": "https://repl.it/talk/share/repldm-alpha-001-direct-messaging-in-replit/124217"
	},
	"social_media_goqpqprm": {
		"title": "Replitsh V3",
		"username": "Piemadd",
		"talk": "",
		"code": "from flask import Flask, render_template, request, redirect, send_from_directory, jsonify\r\nfrom replit import db\r\nimport random, string, json, os, validators, logging, requests\r\nfrom middleware import middleware\r\nfrom pygments.lexers import get_all_lexers\r\nfrom pygments.styles import get_all_styles\r\n\r\nprint_db_on_start = False\r\nexport_db_on_start = False\r\nimport_db_on_start = False\r\n\r\n# Shortener Setup\r\nurl = \"https://replit.sh/\" # URL of Your Site\r\nsiteName = \"Replit.sh\" # Name of your Site"
	},
	"social_media_hdcgnfet": {
		"title": "SortacraftModelMaker",
		"username": "SortaGames",
		"talk": "https://replit.com/talk/share/SortaCraft-Model-Builder-Updated/125566",
		"code": "import * as THREE from '/three.js'; //ALT, threejs was down\r\nimport VoxelWorld from '/VoxelWorld.js'; //Voxel code\r\nimport TextureAtlas from 'https://sortacraft-texturesplit.sortagames.repl.co/script.js'; // texture split\r\nlet camera, scene, renderer, controls, block, ambient, speed = .1, spot, voxelTextures, geometryWorker, chunk, localVoxelWorld, euler = new THREE.Euler(0, 0, 0, 'YXZ'), currentVoxel = 1, clock = new THREE.Clock(), keys = [], vec = new THREE.Vector3(), pointer, pi2 = Math.PI / 2, pointerLocked = false, lights = [], lightMode = false, inv = document.getElementById('inv'),spanStat = document.getElementById('stat'), splitTextures;\r\nwindow.shift = false;\r\n\r\nTextureAtlas.init();\r\nTextureAtlas.done = (arr) => {splitTextures = arr; fillInv()};\r\n\r\n\r\nfunction fillInv() {\r\n  let otherCanv = [];\r\n  // splitTextures.top\r\n  for(let i = 0; i < splitTextures.length; i++){\r\n    let block = splitTextures[i].side; //Taking from side image;\r\n    // remember this: block # = i;\r\n    let img = document.createElement('canvas');\r\n    let ctx = img.getContext('2d');\r\n    img.height = '16';\r\n    img.width = '16';\r\n    ctx.drawImage(block,0,0);\r\n    img.classList.add('img');\r\n    otherCanv.push(img);\r\n    img.addEventListener('mousedown', () => {\r\n      currentVoxel = i+1;"
	},
	"social_media_jovopjlm": {
		"title": "Portfolio Site",
		"username": "CodingCactus",
		"talk": "https://repl.it/talk/share/Portfolio-Site/121985"
	},
	"social_media_joygcaze": {
		"title": "Labyrinth",
		"username": "RhinoRunner",
		"talk": "https://repl.it/talk/share/Labyrinth/122538"
	},
	"social_media_jwcohuqc": {
		"title": "CSS Orbit",
		"username": "KobeFF",
		"talk": "https://repl.it/talk/share/post/119400",
		"code": "body.big-page, #example {\r\n\toverflow: hidden;\r\n\tbackground: url('images/bg.jpg');\r\n  background-size: cover;\r\n}\r\n\r\n.entry img {\r\n\tborder: none;\r\n}\r\n\r\n\r\n#mainContent, #example {\r\n\tposition: relative;\r\n\tdisplay: block;\r\n\twidth: 800px;\r\n\tborder: none;\r\n\tmargin: 0 auto;\r\n\theight: 800px;\r\n\toverflow: visible;\r\n}\r\n\r\n\r\n#sun {\r\n\tposition: absolute;\r\n\tleft: 330px;"
	},
	"social_media_lzogruvo": {
		"title": "CSS Orbit",
		"username": "KobeFF",
		"talk": "https://repl.it/talk/share/post/119400",
		"code": "body.big-page, #example {\r\n\toverflow: hidden;\r\n\tbackground: url('images/bg.jpg');\r\n  background-size: cover;\r\n}\r\n\r\n.entry img {\r\n\tborder: none;\r\n}\r\n\r\n\r\n#mainContent, #example {\r\n\tposition: relative;\r\n\tdisplay: block;\r\n\twidth: 800px;\r\n\tborder: none;\r\n\tmargin: 0 auto;\r\n\theight: 800px;\r\n\toverflow: visible;\r\n}\r\n\r\n\r\n#sun {\r\n\tposition: absolute;\r\n\tleft: 330px;"
	},
	"social_media_milpntsa": {
		"title": "Labyrinth",
		"username": "RhinoRunner",
		"talk": "https://repl.it/talk/share/Labyrinth/122538"
	},
	"social_media_mpkkdbur": {
		"title": "firefox",
		"username": "piemadd",
		"talk": ""
	},
	"social_media_nuogwslz": {
		"title": "Sortacraftmodelmaker",
		"username": "SortaGames",
		"talk": "https://replit.com/talk/share/SortaCraft-Model-Builder-Updated/125566",
		"code": "<!DOCTYPE html>\r\n<html>\r\n  <head>\r\n    <meta charset=\"utf-8\">\r\n    <meta name=\"viewport\" content=\"width=device-width\">\r\n    <title>Model Builder for SortaCraft</title>\r\n    <link href=\"style.css\" rel=\"stylesheet\" type=\"text/css\" />\r\n  </head>\r\n  <body>\r\n    <div id=\"dot\"></div>\r\n    <div id=\"inv\">\r\n      <div class=\"inner\">\r\n        \r\n      </div>\r\n      </div>\r\n    <div id=\"gui\">\r\n      <div class=\"inner\">\r\n        <span id=\"stat\">Click to lock your pointer.</span>\r\n        <br>\r\n        <button onclick=\"saveWorld()\" tabindex=\"-1\">Save</button><br>\r\n        <button onclick=\"loadWorld()\" tabindex=\"-1\">Load</button><br>\r\n        Shift goes down? <input type=\"checkbox\" onchange=\"window.shift = this.checked\">\r\n      </div>\r\n    </div>\r\n    <script src=\"script.js\" type=\"module\"></script>"
	},
	"social_media_pfztxwcd": {
		"title": "Replitsh-V3",
		"username": "Piemadd",
		"talk": "",
		"code": "from flask import Flask, render_template, request, redirect, send_from_directory, jsonify\r\nfrom replit import db\r\nimport random, string, json, os, validators, logging, requests\r\nfrom middleware import middleware\r\nfrom pygments.lexers import get_all_lexers\r\nfrom pygments.styles import get_all_styles\r\n\r\nprint_db_on_start = False\r\nexport_db_on_start = False\r\nimport_db_on_start = False"
	},
	"social_media_qbzxorph": {
		"title": "Replitsh-V3",
		"username": "Piemadd",
		"talk": ""
	},
	"social_media_rjhhtdql": {
		"title": "CSS Orbit",
		"username": "KobeFF",
		"talk": "https://repl.it/talk/share/post/119400",
		"code": "body.big-page, #example {\r\n\toverflow: hidden;\r\n\tbackground: url('images/bg.jpg');\r\n  background-size: cover;\r\n}\r\n\r\n.entry img {\r\n\tborder: none;\r\n}\r\n\r\n\r\n#mainContent, #example {\r\n\tposition: relative;\r\n\tdisplay: block;\r\n\twidth: 800px;\r\n\tborder: none;\r\n\tmargin: 0 auto;\r\n\theight: 800px;\r\n\toverflow: visible;\r\n}\r\n\r\n\r\n#sun {\r\n\tposition: absolute;\r\n\tleft: 330px;"
	},
	"social_media_stgnhpor": {
		"title": "firefox",
		"username": "piemadd",
		"talk": ""
	},
	"social_media_tdogdnml": {
		"title": "AI that will guess your age Beta",
		"username": "galaxyraider9",
		"talk": "https://repl.it/talk/share/AI-that-will-guess-your-age-Beta/123704"
	},
	"social_media_ugvrpvht": {
		"title": "Replitsh-V3",
		"username": "Piemadd",
		"talk": ""
	},
	"social_media_upajzvjp": {
		"title": "Replitsh V3",
		"username": "Piemadd",
		"talk": "",
		"code": "from flask import Flask, render_template, request, redirect, send_from_directory, jsonify\r\nfrom replit import db\r\nimport random, string, json, os, validators, logging, requests\r\nfrom middleware import middleware\r\n\r\nprint_db_on_start = False\r\nexport_db_on_start = False\r\nimport_db_on_start = False\r\n\r\n# Shortener Setup\r\nurl = \"https://replit.sh/\" # URL of Your Site\r\nsiteName = \"Replit.sh\" # Name of your Site\r\n\r\nif print_db_on_start:\r\n\tprint(list(db.keys()))\r\n\r\nif export_db_on_start:\r\n\toutdb = {}\r\n\tprint(\"Starting DB Export...\")\r\n\tfor x in list(db.keys()):\r\n\t\tprint(\"Set key \" + str(x) + \" to \" + str(db[x]))\r\n\t\toutdb[x] = db[x]\r\n\tf = open('out.json', 'w')\r\n\twith open('out.json', 'w') as outfile:\r\n\t\tprint(\"File opened...\")"
	},
	"social_media_wlhhldpl": {
		"title": "Replitsh-v3",
		"username": "piemadd",
		"talk": ""
	},
	"social_media_wlzwdvor": {
		"title": "Replitsh-V3",
		"username": "Piemadd",
		"talk": "",
		"code": "from flask import Flask, render_template, request, redirect, send_from_directory, jsonify\r\nfrom replit import db\r\nimport random, string, json, os, validators, logging, requests\r\nfrom middleware import middleware\r\nfrom pygments.lexers import get_all_lexers\r\nfrom pygments.styles import get_all_styles\r\n\r\nprint_db_on_start = False\r\nexport_db_on_start = False\r\nimport_db_on_start = False\r\n\r\n# Shortener Setup\r\nurl = \"https://replit.sh/\" # URL of Your Site\r\nsiteName = \"Replit.sh\" # Name of your Site"
	},
	"social_media_xrgukhpn": {
		"title": "Gepl-Chat",
		"username": "Crosis",
		"talk": ""
	},
	"social_media_yjmhaahr": {
		"title": "ClutteredSecondhandCookies",
		"username": "Piemadd",
		"talk": "",
		"code": "# bot.py\r\nimport os\r\n\r\n# yeet\r\nimport discord\r\nfrom dotenv import load_dotenv\r\n\r\nload_dotenv()\r\nTOKEN = os.getenv('DISCORD_TOKEN')\r\nGUILD = os.getenv('DISCORD_GUILD')\r\n\r\n# i like trains\r\n\r\nclient = discord.Client()\r\n\r\n@client.event\r\nasync def on_ready():\r\n    for guild in client.guilds:\r\n        if guild.name == GUILD:\r\n            break\r\n\r\n    print(\r\n        f'{client.user} is connected to the following guild:\\n'\r\n        f'{guild.name}(id: {guild.id})'\r\n    )"
	},
	"user_id_1830004": [
		"short_url_zubthmur",
		"short_url_cj10",
		"short_url_accw3",
		"short_url_accw2",
		"short_url_curriculum-pyint",
		"short_url_rtp_2-5-3",
		"short_url_accw5",
		"short_url_curriculum-abdat",
		"short_url_ctzbfnlp",
		"short_url_mmniponi",
		"short_url_accw4",
		"short_url_advoc",
		"short_url_torkey",
		"short_url_lvpoyuhw",
		"short_url_mixtut",
		"short_url_accw6",
		"short_url_accw1",
		"short_url_hbdpiero",
		"short_url_mpkkdbur",
		"short_url_stgnhpor",
		"short_url_wlhhldpl",
		"short_url_cflfotea",
		"short_url_jovopjlm",
		"short_url_xrgukhpn",
		"short_url_ugvrpvht",
		"short_url_joygcaze",
		"short_url_milpntsa",
		"short_url_cmrpkuvz",
		"short_url_tdogdnml",
		"short_url_ftydgwts",
		"short_url_qbzxorph",
		"short_url_pfztxwcd",
		"short_url_ahvwvztw",
		"short_url_wlzwdvor",
		"short_url_goqpqprm",
		"short_url_upajzvjp",
		"short_url_yjmhaahr",
		"short_url_claim-sigcse21",
		"short_url_lzogruvo",
		"short_url_jwcohuqc",
		"short_url_rjhhtdql",
		"short_url_nuogwslz",
		"short_url_hdcgnfet",
		"short_url_diukifyj",
		"short_url_euqsuwjm",
		"short_url_enfeofcb",
		"short_url_cxlyytte",
		"short_url_auvxllnp"
	],
	"user_id_3586693": [
		"short_url_xmsoyyvo",
		"short_url_brfaevjr",
		"short_url_mtvzokiv",
		"short_url_mebrnnua"
	],
	"user_id_3883382": [
		"short_url_replit-data",
		"short_url_replit-new-talent",
		"short_url_replit-intern",
		"short_url_replit-designer",
		"short_url_replit-platform",
		"short_url_replit-product",
		"short_url_replit-sre",
		"short_url_replit-growth",
		"short_url_replit-ed_csm",
		"short_url_replit-teacher-success",
		"short_url_replit-community-social"
	]
}